rpg_xml/__init__.py
rpg_xml/engine.py
rpg_xml/music_controller.py
rpg_xml/music_player.py
rpg_xml/scene_controller.py
rpg_xml/terminal_ui.py
rpg_xml/xmlparser.py
rpg_xml-0.1.2.dist-info/LICENSE
rpg_xml-0.1.2.dist-info/METADATA
rpg_xml-0.1.2.dist-info/WHEEL
rpg_xml-0.1.2.dist-info/top_level.txt
rpg_xml-0.1.2.dist-info/RECORD
