Metadata-Version: 2.1
Name: rpg_xml
Version: 0.1.2
Summary: Crie rpg de texto usando xml!
Author: Kaic Salomão
License-File: LICENSE
